LICENSE
README.md
setup.py
ncbi_tree/__init__.py
ncbi_tree/cli.py
ncbi_tree/core.py
ncbi_tree.egg-info/PKG-INFO
ncbi_tree.egg-info/SOURCES.txt
ncbi_tree.egg-info/dependency_links.txt
ncbi_tree.egg-info/entry_points.txt
ncbi_tree.egg-info/requires.txt
ncbi_tree.egg-info/top_level.txt
tests/test.py