Metadata-Version: 2.4
Name: ncbi-tree
Version: 1.0.1
Summary: ncbi-tree is an open source, cross-platform command-line tool for downloading the latest NCBI taxonomy database and converting it to Newick tree format (.tre), with optional plain-text visualization (.txt)
Home-page: https://github.com/phylobridge/ncbi-tree
Author: NCBI-Tree Contributors
Author-email: 
License: CC BY-NC 4.0
Project-URL: Homepage, https://github.com/phylobridge/ncbi-tree
Project-URL: Documentation, https://github.com/phylobridge/ncbi-tree#readme
Project-URL: Bug Reports, https://github.com/phylobridge/ncbi-tree/issues
Project-URL: Source, https://github.com/phylobridge/ncbi-tree
Project-URL: NCBI Taxonomy, https://www.ncbi.nlm.nih.gov/taxonomy
Keywords: ncbi,taxonomy,phylogeny,bioinformatics,newick,tree,phylogenetic,ncbi-taxonomy,taxdump,taxonomic-tree,species-tree,tree-of-life,phylogenetic-tree,taxonomy-database,taxonomy-parser,taxonomy-analysis,biology,genomics,evolution,evolutionary-biology,systematics,species-classification,organism-classification,taxonomic-hierarchy,computational-biology,metagenomics,biodiversity,clade-analysis,taxon-names,taxonomy-ids,merged-taxa,rank-distribution,phylogenetics,phylogenomics,comparative-genomics
Classifier: Development Status :: 5 - Production/Stable
Classifier: Intended Audience :: Science/Research
Classifier: Intended Audience :: Developers
Classifier: Intended Audience :: Education
Classifier: Intended Audience :: Healthcare Industry
Classifier: License :: Free for non-commercial use
Classifier: Operating System :: OS Independent
Classifier: Operating System :: POSIX :: Linux
Classifier: Operating System :: MacOS
Classifier: Operating System :: Microsoft :: Windows
Classifier: Programming Language :: Python :: 3
Classifier: Programming Language :: Python :: 3.8
Classifier: Programming Language :: Python :: 3.9
Classifier: Programming Language :: Python :: 3.10
Classifier: Programming Language :: Python :: 3.11
Classifier: Programming Language :: Python :: 3.12
Classifier: Programming Language :: Python :: 3.13
Classifier: Topic :: Scientific/Engineering :: Bio-Informatics
Classifier: Topic :: Scientific/Engineering :: Information Analysis
Classifier: Topic :: Scientific/Engineering :: Visualization
Classifier: Topic :: Software Development :: Libraries :: Python Modules
Classifier: Topic :: Database
Classifier: Environment :: Console
Classifier: Natural Language :: English
Requires-Python: >=3.8
License-File: LICENSE
Requires-Dist: requests>=2.25.0
Requires-Dist: tqdm>=4.50.0
Dynamic: author
Dynamic: classifier
Dynamic: description
Dynamic: description-content-type
Dynamic: home-page
Dynamic: keywords
Dynamic: license
Dynamic: license-file
Dynamic: project-url
Dynamic: requires-dist
Dynamic: requires-python
Dynamic: summary
